pydockrmsd/__init__.py
pydockrmsd/__version__.py
pydockrmsd/dockrmsd.pypy36-pp73-darwin.so
pydockrmsd/hungarian.py
pydockrmsd-1.0.0.dist-info/LICENSE
pydockrmsd-1.0.0.dist-info/METADATA
pydockrmsd-1.0.0.dist-info/WHEEL
pydockrmsd-1.0.0.dist-info/top_level.txt
pydockrmsd-1.0.0.dist-info/RECORD
